[
    {
        "name":"PHP"
    },
    {
        "name":"PKR"
    },
    {
        "name":"RUB"
    },
    {
        "name":"THB"
    },
    {
        "name":"UAB"
    },
    {
        "name":"ZND"
    },
    {
        "name":"VER"
    },
    {
        "name":"PHP"
    },
    {
        "name":"PKR"
    },
    {
        "name":"RUB"
    },
    {
        "name":"THB"
    },
    {
        "name":"UAB"
    },
    {
        "name":"ZND"
    },
    {
        "name":"VER"
    },
    {
        "name":"EUR"   
    }
]